cli.py
context.py
constants/__init__.py
constants/ai.py
constants/cli.py
utils/__init__.py
utils/ai.py
utils/stream.py
utils/utils.py
fleet_context-1.1.9.dist-info/LICENSE
fleet_context-1.1.9.dist-info/METADATA
fleet_context-1.1.9.dist-info/WHEEL
fleet_context-1.1.9.dist-info/entry_points.txt
fleet_context-1.1.9.dist-info/top_level.txt
fleet_context-1.1.9.dist-info/RECORD
