Metadata-Version: 2.1
Name: fleet-context
Version: 1.1.9
Summary: A chat interface over up-to-date Python library documentation.
Home-page: https://github.com/fleet-ai/context/tree/main
Author: Fleet AI
Author-email: Fleet AI <team@fleet.so>
Maintainer-email: Nic Ouporov <nic@fleet.so>, Alec Jo <alec@fleet.so>, Andrew Zhou <andrew@fleet.so>
Project-URL: Homepage, https://fleet.so
Project-URL: Source, https://github.com/fleet-ai/context
Keywords: libraries,embeddings,ai
Classifier: Development Status :: 4 - Beta
Classifier: Intended Audience :: Developers
Classifier: Topic :: Software Development :: Build Tools
Classifier: License :: OSI Approved :: MIT License
Classifier: Programming Language :: Python :: 3
Classifier: Programming Language :: Python :: 3.9
Classifier: Programming Language :: Python :: 3.10
Classifier: Programming Language :: Python :: 3.11
Classifier: Programming Language :: Python :: 3 :: Only
Requires-Python: >=3.9
License-File: LICENSE
Requires-Dist: openai (>1.1.0)
Requires-Dist: rich (>=13.0.0)
Requires-Dist: tiktoken (>=0.3.3)
